add_scalebar/__init__.py
add_scalebar/__main__.py
add_scalebar/addScaleBarGUI.py
test_em_add_scalebar-0.0.1.dist-info/LICENSE.txt
test_em_add_scalebar-0.0.1.dist-info/METADATA
test_em_add_scalebar-0.0.1.dist-info/WHEEL
test_em_add_scalebar-0.0.1.dist-info/top_level.txt
test_em_add_scalebar-0.0.1.dist-info/RECORD
