Metadata-Version: 2.1
Name: test-em-add-scalebar
Version: 0.0.1
Summary: A package to add a scale bar to microscopy images
Home-page: https://git.mpi-cbg.de/scicomp/bioimage_team/tobias_em_app_scalebar
Author: Anthony Vega
Author-email: vega@extern.mpi-cbg.de
License: BSD
Platform: UNKNOWN
Classifier: Development Status :: 1 - Planning
Classifier: Intended Audience :: Science/Research
Classifier: License :: OSI Approved :: BSD License
Classifier: Operating System :: MacOS
Classifier: Programming Language :: Python :: 3
Classifier: Programming Language :: Python :: 3.10
License-File: LICENSE.txt
Requires-Dist: numpy (==1.23.5)
Requires-Dist: scikit-image
Requires-Dist: matplotlib (==3.7.0)
Requires-Dist: microfilm (==0.2.1)
Requires-Dist: aicsimageio (==4.14.0)
Requires-Dist: opencv-python
Requires-Dist: mrcfile
Requires-Dist: Gooey (>=1.0.7)
